Metadata-Version: 1.1
Name: drip-py
Version: 0.1
Summary: A Python wrapper for getdrip.com REST API.
Home-page: https://www.springboard.com/
Author: Springboard Tech Team
Author-email: jeet@springboard.com
License: MIT License
Platform: UNKNOWN
Classifier: Environment :: Web Environment
Classifier: Intended Audience :: Developers
Classifier: License :: OSI Approved :: MIT License
Classifier: Natural Language :: English
Classifier: Operating System :: OS Independent
Classifier: Programming Language :: Python
Classifier: Programming Language :: Python :: 2.7
Classifier: Programming Language :: Python :: 3
Classifier: Programming Language :: Python :: 3
Classifier: Programming Language :: Python :: 3.4
Classifier: Programming Language :: Python :: 3.5
Classifier: Topic :: Communications :: Email
Classifier: Topic :: Communications :: Email :: Mailing List Servers
